_bo4e-dotnet-generator_version.py
bo4egenerator/__init__.py
bo4egenerator/cli.py
bo4egenerator/duplicates.py
bo4egenerator/generator.py
bo4egenerator/py.typed
bo4egenerator/tooling.py
dotnet-classes/ZusatzAttribut.cs
dotnet-classes/bo/Angebot.cs
dotnet-classes/bo/Ausschreibung.cs
dotnet-classes/bo/Buendelvertrag.cs
dotnet-classes/bo/Energiemenge.cs
dotnet-classes/bo/Fremdkosten.cs
dotnet-classes/bo/Geraet.cs
dotnet-classes/bo/Geschaeftspartner.cs
dotnet-classes/bo/Kosten.cs
dotnet-classes/bo/Lastgang.cs
dotnet-classes/bo/Marktlokation.cs
dotnet-classes/bo/Marktteilnehmer.cs
dotnet-classes/bo/Messlokation.cs
dotnet-classes/bo/Person.cs
dotnet-classes/bo/Preisblatt.cs
dotnet-classes/bo/PreisblattDienstleistung.cs
dotnet-classes/bo/PreisblattHardware.cs
dotnet-classes/bo/PreisblattKonzessionsabgabe.cs
dotnet-classes/bo/PreisblattMessung.cs
dotnet-classes/bo/PreisblattNetznutzung.cs
dotnet-classes/bo/Rechnung.cs
dotnet-classes/bo/Region.cs
dotnet-classes/bo/Regionaltarif.cs
dotnet-classes/bo/Standorteigenschaften.cs
dotnet-classes/bo/Tarif.cs
dotnet-classes/bo/Tarifinfo.cs
dotnet-classes/bo/Tarifkosten.cs
dotnet-classes/bo/Tarifpreisblatt.cs
dotnet-classes/bo/Vertrag.cs
dotnet-classes/bo/Zaehler.cs
dotnet-classes/bo/Zeitreihe.cs
dotnet-classes/com/Adresse.cs
dotnet-classes/com/Angebotsposition.cs
dotnet-classes/com/Angebotsteil.cs
dotnet-classes/com/Angebotsvariante.cs
dotnet-classes/com/AufAbschlag.cs
dotnet-classes/com/AufAbschlagProOrt.cs
dotnet-classes/com/AufAbschlagRegional.cs
dotnet-classes/com/AufAbschlagstaffelProOrt.cs
dotnet-classes/com/Ausschreibungsdetail.cs
dotnet-classes/com/Ausschreibungslos.cs
dotnet-classes/com/Betrag.cs
dotnet-classes/com/Dienstleistung.cs
dotnet-classes/com/Energieherkunft.cs
dotnet-classes/com/Energiemix.cs
dotnet-classes/com/Fremdkostenblock.cs
dotnet-classes/com/Fremdkostenposition.cs
dotnet-classes/com/Geokoordinaten.cs
dotnet-classes/com/Katasteradresse.cs
dotnet-classes/com/Kontaktweg.cs
dotnet-classes/com/Konzessionsabgabe.cs
bo4e_dotnet_generator-0.0.3.dist-info/METADATA
bo4e_dotnet_generator-0.0.3.dist-info/WHEEL
bo4e_dotnet_generator-0.0.3.dist-info/entry_points.txt
bo4e_dotnet_generator-0.0.3.dist-info/licenses/LICENSE
bo4e_dotnet_generator-0.0.3.dist-info/RECORD
