Metadata-Version: 2.3
Name: bo4e-dotnet-generator
Version: 0.0.3
Summary: Generates C# Classes from JSON schemas for a 100% code-generated BO4E.NEt v2
Project-URL: Changelog, https://github.com/Hochfrequenz/bo4e-dotnet-generator.py/releases
Project-URL: Homepage, https://github.com/Hochfrequenz/bo4e-dotnet-generator.py
Author-email: Hamid Hajiparvaneh <info+github@hochfrequenz.de>
License: MIT
License-File: LICENSE
Keywords: BO4E,Code Generation,JSON schema
Classifier: Development Status :: 4 - Beta
Classifier: Environment :: Console
Classifier: Intended Audience :: Developers
Classifier: License :: OSI Approved :: MIT License
Classifier: Operating System :: OS Independent
Classifier: Programming Language :: Python
Classifier: Programming Language :: Python :: 3 :: Only
Classifier: Programming Language :: Python :: 3.11
Classifier: Programming Language :: Python :: 3.12
Requires-Python: >=3.11
Requires-Dist: bo4e-schema-tool>=0.0.7
Requires-Dist: typer
